code_context_compiler/__init__.py
code_context_compiler/ai_prompt.py
code_context_compiler/cli.py
code_context_compiler/config.py
code_context_compiler/masker.py
code_context_compiler/scraper.py
code_context_compiler-0.1.4.dist-info/LICENSE
code_context_compiler-0.1.4.dist-info/METADATA
code_context_compiler-0.1.4.dist-info/WHEEL
code_context_compiler-0.1.4.dist-info/entry_points.txt
code_context_compiler-0.1.4.dist-info/RECORD
