Metadata-Version: 2.1
Name: code_context_compiler
Version: 0.1.4
Summary: A CLI tool to scan a code project and create a single file with the entire project code, ideal for feeding context to LLMs.
Home-page: https://github.com/chetanchoudhary/code_context_compiler
License: MIT
Keywords: cli,code,compiler,context,llm,ai
Author: Chetan Choudhary
Author-email: chetan.choudhary.office@gmail.com
Requires-Python: >=3.8,<4.0
Classifier: Development Status :: 3 - Alpha
Classifier: Intended Audience :: Developers
Classifier: License :: OSI Approved :: MIT License
Classifier: Programming Language :: Python :: 3
Classifier: Programming Language :: Python :: 3.8
Classifier: Programming Language :: Python :: 3.9
Classifier: Programming Language :: Python :: 3.10
Classifier: Programming Language :: Python :: 3.11
Classifier: Programming Language :: Python :: 3.12
Requires-Dist: aiofiles (>=0.8.0,<0.9.0)
Requires-Dist: gitpython (>=3.1.18,<4.0.0)
Requires-Dist: pathspec (>=0.9.0,<0.10.0)
Requires-Dist: pyyaml (>=6.0,<7.0)
Requires-Dist: rich (>=10.12.0,<11.0.0)
Requires-Dist: typer (>=0.6.1,<0.7.0)
Project-URL: Repository, https://github.com/chetanchoudhary/code_context_compiler
